meteolab/__init__.py
meteolab/__main__.py
meteolab/main.py
meteolab-0.3.0.dist-info/LICENSE
meteolab-0.3.0.dist-info/METADATA
meteolab-0.3.0.dist-info/WHEEL
meteolab-0.3.0.dist-info/entry_points.txt
meteolab-0.3.0.dist-info/top_level.txt
meteolab-0.3.0.dist-info/RECORD
